ampapi/__init__.py
ampapi/ampapi.py
ampapi/auth.py
ampapi/modules.py
ampapi/plugins.py
ampapi/types.py
ampapi-2620.5.0.dist-info/METADATA
ampapi-2620.5.0.dist-info/WHEEL
ampapi-2620.5.0.dist-info/top_level.txt
ampapi-2620.5.0.dist-info/RECORD
