Metadata-Version: 2.4
Name: ampapi
Version: 2620.5.0
Summary: An API that allows you to communicate with AMP installations from within Python.
Home-page: https://github.com/p0t4t0sandwich/ampapi
Author: Dylan Sperrer - p0t4t0sandwich - thepotatoking3452
Author-email: p0t4t0sandwich@gmail.com
Classifier: Programming Language :: Python :: 3
Classifier: License :: OSI Approved :: Apache Software License
Classifier: Operating System :: OS Independent
Requires-Python: >=3.8
